globallock/__init__.py
globallock/base.py
globallock/config.py
globallock/constants.py
globallock/django.py
globallock/django_redis_global_lock.py
globallock/etcd_global_lock.py
globallock/exceptions.py
globallock/redis_global_lock.py
globallock/zookeeper_global_lock.py
globallock-0.1.4.dist-info/licenses/LICENSE
globallock-0.1.4.dist-info/METADATA
globallock-0.1.4.dist-info/WHEEL
globallock-0.1.4.dist-info/top_level.txt
globallock-0.1.4.dist-info/RECORD
