Metadata-Version: 2.4
Name: globallock
Version: 0.1.4
Summary: Distributed lock manager, support many types of backend, e.g. redis, django-redis, etcd, zookeeper...
Author: rRR0VrFP
Maintainer: rRR0VrFP
License: MIT
Keywords: global lock,distributed lock,redis lock,django redis lock,zookeeper lock,etcd lock
Classifier: Development Status :: 5 - Production/Stable
Classifier: Intended Audience :: Developers
Classifier: Topic :: Software Development :: Libraries :: Python Modules
Classifier: License :: OSI Approved :: MIT License
Classifier: Programming Language :: Python :: 3
Classifier: Programming Language :: Python :: 3 :: Only
Requires-Python: >=3.6
License-File: LICENSE
Requires-Dist: zenutils
Dynamic: author
Dynamic: classifier
Dynamic: description
Dynamic: description-content-type
Dynamic: keywords
Dynamic: license
Dynamic: license-file
Dynamic: maintainer
Dynamic: requires-dist
Dynamic: requires-python
Dynamic: summary
